collective.remoteproxy-2.0-py3.7-nspkg.pth
collective/remoteproxy/__init__.py
collective/remoteproxy/behaviors.py
collective/remoteproxy/configure.zcml
collective/remoteproxy/interfaces.py
collective/remoteproxy/remoteproxy.py
collective/remoteproxy/setuphandlers.py
collective/remoteproxy/testing.py
collective/remoteproxy/traverser.py
collective/remoteproxy/browser/__init__.py
collective/remoteproxy/browser/common.py
collective/remoteproxy/browser/configure.zcml
collective/remoteproxy/browser/tile.pt
collective/remoteproxy/browser/view.pt
collective/remoteproxy/locales/collective.proxytype.pot
collective/remoteproxy/locales/update.sh
collective/remoteproxy/portlets/__init__.py
collective/remoteproxy/portlets/configure.zcml
collective/remoteproxy/portlets/portlet.pt
collective/remoteproxy/portlets/portlet.py
collective/remoteproxy/profiles/default/metadata.xml
collective/remoteproxy/profiles/default/portlets.xml
collective/remoteproxy/profiles/default/types.xml
collective/remoteproxy/profiles/default/types/RemoteProxy.xml
collective/remoteproxy/profiles/uninstall/browserlayer.xml
collective/remoteproxy/profiles/uninstall/portlets.xml
collective/remoteproxy/profiles/uninstall/types.xml
collective/remoteproxy/tests/__init__.py
collective/remoteproxy/tests/test_proxy.py
collective/remoteproxy/tests/test_robot.py
collective/remoteproxy/tests/test_setup.py
collective/remoteproxy/tests/robot/test_proxy.robot
collective.remoteproxy-2.0.dist-info/METADATA
collective.remoteproxy-2.0.dist-info/WHEEL
collective.remoteproxy-2.0.dist-info/entry_points.txt
collective.remoteproxy-2.0.dist-info/namespace_packages.txt
collective.remoteproxy-2.0.dist-info/top_level.txt
collective.remoteproxy-2.0.dist-info/RECORD
