Metadata-Version: 2.1
Name: collective.remoteproxy
Version: 2.0
Summary: Proxy for remote content in Plone pages.
Home-page: https://github.com/collective/collective.remoteproxy
Author: Johannes Raggam
Author-email: thetetet@gmail.com
License: GPL
Keywords: proxy content remote
Platform: UNKNOWN
Classifier: Development Status :: 5 - Production/Stable
Classifier: Environment :: Web Environment
Classifier: Framework :: Plone
Classifier: Framework :: Plone :: 5.2
Classifier: Framework :: Plone :: 6.0
Classifier: Framework :: Plone :: Addon
Classifier: Framework :: Zope
Classifier: Framework :: Zope :: 4
Classifier: Framework :: Zope :: 5
Classifier: License :: OSI Approved :: GNU General Public License v2 (GPLv2)
Classifier: Operating System :: OS Independent
Classifier: Programming Language :: Python
Classifier: Programming Language :: Python
Classifier: Programming Language :: Python :: 3.6
Classifier: Programming Language :: Python :: 3.7
Classifier: Programming Language :: Python :: 3.8
Requires-Dist: setuptools
Requires-Dist: Products.CMFCore
Requires-Dist: plone.tiles
Provides-Extra: test
Requires-Dist: plone.app.testing ; extra == 'test'
Requires-Dist: plone.app.robotframework ; extra == 'test'
